{
  "title": "更年期に使われる漢方薬おすすめ5選｜症状別の選び方",
  "content": "# 更年期に使われる漢方薬おすすめ5選｜症状別の選び方\n\n> ※本記事は一般的な情報提供を目的としており、医療アドバイスではありません。症状が続く場合は医師・薬剤師にご相談ください。\n\n## この記事の結論\n\n- **更年期症状に用いられる漢方薬は「三大婦人薬」が基本**——加味逍遙散・当帰芍薬散・桂枝茯苓丸の3処方\n- **症状と体質で選ぶのが漢方のセオリー**——「更年期だからこれ」ではなく、虚実・気血水のバランスで処方が変わる\n- **漢方はホルモン補充療法（HRT）との併用も可能**——西洋医学と東洋医学の「いいとこ取り」ができる\n\n## 漢方の視点で解説\n\n漢方医学では更年期を「腎虚（じんきょ）」——生命エネルギーの根本である「腎」の力が自然に衰えていく過程と捉えます。これは病気ではなく、生命の自然な変化です。\n\n更年期に起こる多彩な症状は、腎虚をベースに**気の上衝（のぼせ・ほてり）**、**血虚（貧血傾向・乾燥）**、**瘀血（肩こり・頭痛）**、**水滞（むくみ・めまい）**が複合的に現れたものと解釈されます。\n\nだからこそ、漢方では「更年期＝この薬」という画一的な処方ではなく、**その人の体質と症状のパターンに応じた個別処方**が重視されます。\n\n## 具体的な処方と使い分け\n\n| 処方名 | ツムラ番号 | 体質 | 主な症状 |\n|--------|-----------|------|----------|\n| **加味逍遙散（かみしょうようさん）** | 24番 | 虚〜中間証 | イライラ、不眠、ホットフラッシュ、肩こり |\n| **当帰芍薬散（とうきしゃくやくさん）** | 23番 | 虚証 | 冷え、むくみ、疲れやすい、めまい |\n| **桂枝茯苓丸（けいしぶくりょうがん）** | 25番 | 実証 | のぼせ、頭痛、肩こり、足の冷え |\n| **温経湯（うんけいとう）** | 106番 | 虚証 | 手足のほてり、唇の乾燥、冷えのぼせ |\n| **抑肝散（よくかんさん）** | 54番 | 虚〜中間証 | 怒りっぽい、不眠、神経過敏 |\n\n### 症状別の選び方フローチャート\n\n1. **イライラ・精神不安が強い** → 加味逍遙散 or 抑肝散\n2. **冷え・むくみ・疲労が中心** → 当帰芍薬散\n3. **のぼせ・頭痛・肩こりが中心** → 桂枝茯苓丸\n4. **手足のほてり・乾燥** → 温経湯\n\n## 知っておきたい注意点\n\n- **加味逍遙散・当帰芍薬散には甘草が含まれる**——長期服用時は偽アルドステロン症に注意\n- 症状が複数ある場合は、最もつらい症状を優先して処方を選ぶ\n- 漢方薬の効果発現には2〜4週間かかることが一般的——すぐに効果を感じなくても焦らない\n- **乳がん既往のある方はHRTが使えないケースが多く、漢方が第一選択になることも**——必ず主治医と相談を\n- 市販品と医療用では生薬の配合量が異なる場合がある\n\n※個人の感想であり、効果を保証するものではありません。\n\n## マニアックメモ\n\n「三大婦人薬」は日本独自の分類です。中国では更年期に「六味地黄丸（ろくみじおうがん）」系の「補腎（ほじん）」処方が主流ですが、日本では血と水に着目した処方が好まれます。これは日本人女性の体質傾向（虚証が多い）を反映した結果とされています。\n\n興味深いことに、加味逍遙散の「逍遙（しょうよう）」は「気ままにぶらつく」という意味。気の巡りを改善して心を自由にする、という処方の本質を表す美しい名前です。出典は宋代の『太平恵民和剤局方（たいへいけいみんわざいきょくほう）』。\n\n参考：日本産科婦人科学会ガイドライン、ツムラ各処方添付文書\n\n## まとめ：こんな人におすすめ\n\n- **更年期の多彩な症状**に悩んでいる40〜60代の女性\n- HRTに抵抗がある、または使えない事情がある人\n- 「なんとなく不調」を体質から根本的に整えたい人\n- 西洋医学と漢方を組み合わせたアプローチに興味がある人\n\n{{internal_link:加味逍遙散の詳しい解説}}\n{{internal_link:冷え性タイプ別漢方ガイド}}\n{{internal_link:漢方薬の効果が出るまでの期間}}\n\n> ※症状が続く場合は医師・薬剤師にご相談ください。",
  "meta_description": "更年期に用いられる漢方薬おすすめ5選を症状・体質別に解説。三大婦人薬の使い分け、注意点、HRTとの併用まで詳しくガイド。",
  "tags": [
    "更年期",
    "漢方薬",
    "加味逍遙散",
    "三大婦人薬",
    "ホットフラッシュ"
  ],
  "slug": "kounenki-kampo-osusume",
  "category": "症状別漢方ガイド"
}